smlibppm/__init__.py
smlibppm/api/__init__.py
smlibppm/core/__init__.py
smlibppm/core/circle.py
smlibppm/core/error.py
smlibppm/core/line.py
smlibppm/core/noise.py
smlibppm/core/pixel.py
smlibppm/core/png.py
smlibppm/core/ppm.py
smlibppm/core/rect.py
smlibppm/core/triangle.py
smlibppm/core/utils.py
smlibppm-0.1.0.dist-info/LICENSE
smlibppm-0.1.0.dist-info/WHEEL
smlibppm-0.1.0.dist-info/METADATA
smlibppm-0.1.0.dist-info/RECORD
