Metadata-Version: 2.1
Name: smlibppm
Version: 0.1.0
Summary: A small library for creating and manipulating PPMs
License: MIT
Author: Nathan Reed
Author-email: nreed@linux.com
Requires-Python: >=3.9,<4.0
Classifier: License :: OSI Approved :: MIT License
Classifier: Programming Language :: Python :: 3
Classifier: Programming Language :: Python :: 3.10
Classifier: Programming Language :: Python :: 3.9
